video_compressor/__init__.py
video_compressor/compressor.py
video_compressor/exceptions.py
video_compressor/functions.py
video_compressor/skeleton.py
video_compressor/video.py
video_compressor/adapters/__init__.py
video_compressor/adapters/ffmpeg.py
video_compressor-0.0.6.dist-info/AUTHORS.rst
video_compressor-0.0.6.dist-info/LICENSE.txt
video_compressor-0.0.6.dist-info/METADATA
video_compressor-0.0.6.dist-info/WHEEL
video_compressor-0.0.6.dist-info/top_level.txt
video_compressor-0.0.6.dist-info/RECORD
