Metadata-Version: 2.1
Name: video-compressor
Version: 0.0.6
Summary: Simple python video compressor
Home-page: https://github.com/pyscaffold/pyscaffold/
Author: Lenselle Nicolas
Author-email: nicolas@atelierdunumerique.Io
License: mit
Project-URL: Documentation, https://pyscaffold.org/
Platform: any
Classifier: Development Status :: 4 - Beta
Classifier: Programming Language :: Python
Provides-Extra: testing
Requires-Dist: pytest ; extra == 'testing'
Requires-Dist: pytest-cov ; extra == 'testing'
